{
    "type": "carousel",
    "contents": [
      {
        "type": "bubble",
        "hero": {
          "type": "image",
          "size": "full",
          "aspectRatio": "20:19",
          "aspectMode": "cover",
          "url": "https://i.imgur.com/7cslMbN.png"
        },
        "body": {
          "type": "box",
          "layout": "vertical",
          "spacing": "sm",
          "contents": [
            {
              "type": "text",
              "text": "特色中心",
              "wrap": true,
              "weight": "bold",
              "size": "xl"
            },
            {
              "type": "box",
              "layout": "baseline",
              "contents": [
                {
                  "type": "text",
                  "text": "請選擇以下要掛號之科別",
                  "wrap": true,
                  "weight": "regular",
                  "size": "lg",
                  "flex": 0,
                  "color": "#555555"
                }
              ]
            }
          ]
        },
        "footer": {
          "type": "box",
          "layout": "vertical",
          "spacing": "sm",
          "contents": [
            {
              "type": "button",
              "action": {
                "type": "uri",
                "label": "智慧科學體重管理中心",
                "uri": "https://www.hospital.fju.edu.tw/OPDSchedule?SelectID=PEDO#cond&gsc.tab=0"
              }
            },
            {
              "type": "button",
              "action": {
                "type": "uri",
                "label": "聖路加美容中心",
                "uri": "https://www.hospital.fju.edu.tw/OPDSchedule?SelectID=AMC%20#cond&gsc.tab=0"
              }
            },
            {
              "type": "button",
              "action": {
                "type": "uri",
                "label": "腦血管介入治療",
                "uri": "https://www.hospital.fju.edu.tw/OPDSchedule?SelectID=NSRA#cond&gsc.tab=0"
              }
            },
            {
              "type": "button",
              "action": {
                "type": "uri",
                "label": "運動醫學中心",
                "uri": "https://www.hospital.fju.edu.tw/OPDSchedule?SelectID=EXE1#cond&gsc.tab=0"
              }
            },
            {
              "type": "button",
              "action": {
                "type": "uri",
                "label": "營養諮詢",
                "uri": "https://www.hospital.fju.edu.tw/OPDSchedule?SelectID=DIET#cond&gsc.tab=0"
              }
            }
          ]
        }
      }
    ]
  }